Formulix/__init__.py
Formulix/physics.py
Formulix/shapes.py
formulix-0.2.dist-info/METADATA
formulix-0.2.dist-info/WHEEL
formulix-0.2.dist-info/top_level.txt
formulix-0.2.dist-info/RECORD
