Metadata-Version: 2.4
Name: Formulix
Version: 0.2
Summary: A toolkit of geometry and physics formulas
Author: Darsh Nayak Das
Author-email: darsh.nayak@outlook.com
Keywords: geometry,physics,formulas,science,education
Classifier: Programming Language :: Python :: 3
Classifier: License :: OSI Approved :: MIT License
Classifier: Operating System :: OS Independent
Classifier: Intended Audience :: Education
Classifier: Topic :: Scientific/Engineering :: Mathematics
Requires-Python: >=3.6
Dynamic: author
Dynamic: author-email
Dynamic: classifier
Dynamic: description
Dynamic: description-content-type
Dynamic: keywords
Dynamic: requires-python
Dynamic: summary
